Metadata-Version: 2.1
Name: picswaifu
Version: 1.1.0
Home-page: https://gist.github.com/fswair/d1306ae27e13fa90210b3f16832ec218
Author: fswair
Requires-Python: >=3.8
